prsdm/__init__.py
prsdm/operations.py
prsdm-2.0.1.dist-info/METADATA
prsdm-2.0.1.dist-info/WHEEL
prsdm-2.0.1.dist-info/licenses/LICENSE
prsdm-2.0.1.dist-info/RECORD
