Metadata-Version: 2.4
Name: prsdm
Version: 2.0.1
Summary: Mathematical Operations
Project-URL: Homepage, https://github.com/hypertic-ai/test
Project-URL: Repository, https://github.com/hypertic-ai/test
Author-email: prasad mahamulkar <prsd.mahamulkar@gmail.com>
License: Apache-2.0
License-File: LICENSE
Classifier: Intended Audience :: Developers
Classifier: License :: OSI Approved :: Apache Software License
Classifier: Operating System :: OS Independent
Classifier: Programming Language :: Python :: 3
Classifier: Programming Language :: Python :: 3.10
Classifier: Programming Language :: Python :: 3.11
Classifier: Programming Language :: Python :: 3.12
Classifier: Programming Language :: Python :: 3.13
Classifier: Topic :: Software Development :: Libraries :: Python Modules
Requires-Python: >=3.10
Requires-Dist: matplotlib<4,>=3.8.0
Requires-Dist: numpy>=2.2.6
Requires-Dist: pandas<3,>=2.1.0
Requires-Dist: scikit-learn<2,>=1.3.0
Requires-Dist: scipy<2,>=1.11.0
Requires-Dist: seaborn<1,>=0.13.0
